LICENSE.txt
MANIFEST.in
README.rst
setup.cfg
setup.py
webextaware/__init__.py
webextaware/amo.py
webextaware/database.py
webextaware/main.py
webextaware/metadata.py
webextaware/package.json
webextaware/scanner.py
webextaware/webext.py
webextaware.egg-info/PKG-INFO
webextaware.egg-info/SOURCES.txt
webextaware.egg-info/dependency_links.txt
webextaware.egg-info/entry_points.txt
webextaware.egg-info/not-zip-safe
webextaware.egg-info/requires.txt
webextaware.egg-info/top_level.txt
webextaware/modes/__init__.py
webextaware/modes/get.py
webextaware/modes/grep.py
webextaware/modes/info.py
webextaware/modes/libs.py
webextaware/modes/manifest.py
webextaware/modes/meta.py
webextaware/modes/query.py
webextaware/modes/runmode.py
webextaware/modes/scan.py
webextaware/modes/shell.py
webextaware/modes/stats.py
webextaware/modes/sync.py
webextaware/modes/unzip.py