Metadata-Version: 2.1
Name: webextaware
Version: 1.2.5
Summary: Mozilla WebExtensions Security Analyzer
Home-page: https://github.com/cr/webextaware
Author: Christiane Ruetten
Author-email: cr@mozilla.com
License: MPL2
Download-URL: https://github.com/cr/webextaware/archive/latest.tar.gz
Keywords: mozilla,firefox,browser,addons,web extensions,testing,security
Platform: UNKNOWN
Classifier: Development Status :: 4 - Beta
Classifier: Environment :: Console
Classifier: Intended Audience :: Developers
Classifier: License :: OSI Approved :: Mozilla Public License 2.0 (MPL 2.0)
Classifier: Natural Language :: English
Classifier: Operating System :: MacOS :: MacOS X
Classifier: Operating System :: POSIX :: Linux
Classifier: Programming Language :: Python :: 3
Classifier: Programming Language :: Python :: 3 :: Only
Classifier: Topic :: Security
Classifier: Topic :: Software Development :: Quality Assurance
Classifier: Topic :: Software Development :: Testing
Classifier: Topic :: Utilities
Provides-Extra: dev
